LICENSE
README.md
setup.py
esapp_upload/__init__.py
esapp_upload/main.py
esapp_upload/upload.py
esapp_upload.egg-info/PKG-INFO
esapp_upload.egg-info/SOURCES.txt
esapp_upload.egg-info/dependency_links.txt
esapp_upload.egg-info/entry_points.txt
esapp_upload.egg-info/requires.txt
esapp_upload.egg-info/top_level.txt