Metadata-Version: 2.1
Name: esapp-upload
Version: 1.0.3
Summary: A library to compress directories and upload them to ES application server
Home-page: https://gitee.com/chenddcoder/esapp-upload.git
Author: chenddcoder
Author-email: chenddcoder@foxmail.com
Classifier: Programming Language :: Python :: 3
Classifier: License :: OSI Approved :: MIT License
Classifier: Operating System :: OS Independent
Requires-Python: >=3.6
License-File: LICENSE
